makeitaquote/__init__.py
makeitaquote/config.py
makeitaquote/miq.py
makeitaquote/utils.py
makeitaquote-1.1.0.dist-info/licenses/LICENSE
makeitaquote-1.1.0.dist-info/METADATA
makeitaquote-1.1.0.dist-info/WHEEL
makeitaquote-1.1.0.dist-info/top_level.txt
makeitaquote-1.1.0.dist-info/RECORD
